Disinfect-0.2.1.dist-info/DESCRIPTION.rst
Disinfect-0.2.1.dist-info/METADATA
Disinfect-0.2.1.dist-info/RECORD
Disinfect-0.2.1.dist-info/WHEEL
Disinfect-0.2.1.dist-info/metadata.json
Disinfect-0.2.1.dist-info/top_level.txt
disinfect/__init__.py
disinfect/disinfect.py
disinfect/tests.py
