Metadata-Version: 2.0
Name: Disinfect
Version: 0.2.1
Summary: Disinfect: Destroy bad input.
Home-page: https://github.com/corverdevelopment/Disinfect/
Author: Nils Corver
Author-email: nils@corverdevelopment.nl
License: MIT
Keywords: about,this,package
Platform: UNKNOWN
Classifier: Development Status :: 3 - Alpha
Classifier: Intended Audience :: Developers
Classifier: Natural Language :: English
Classifier: License :: OSI Approved :: MIT License
Classifier: Operating System :: OS Independent
Classifier: Programming Language :: Python
Classifier: Programming Language :: Python :: 2
Classifier: Programming Language :: Python :: 2.7
Classifier: Programming Language :: Python :: 3
Classifier: Programming Language :: Python :: 3.5
Classifier: Programming Language :: Python :: Implementation :: CPython
Classifier: Topic :: Software Development :: Libraries :: Python Modules
Requires-Dist: Pandora (>=0.1.13)
Requires-Dist: Poort (>=0.1.4)
Requires-Dist: bleach (>=1.4.2)
Requires-Dist: validate-email-address (>=1)
